{"dependencies":[{"name":"./src/app.js","dynamic":true}],"generated":{"html":"<!DOCTYPE html>\n<html lang=\"en\">\n<head>\n    <meta charset=\"UTF-8\">\n    <meta name=\"viewport\" content=\"width=device-width, initial-scale=1.0\">\n    <meta http-equiv=\"X-UA-Compatible\" content=\"ie=edge\">\n    <title>Chat App</title>\n</head>\n<body>\n    <div id=\"root\"></div>\n    <script src=\"/8848bf40eecb5208ddd0ec99997bb6bc.js\"></script>\n</body>\n</html>"},"hash":"69333c3345254489df07104f3f8579c8","cacheData":{}}